oda_data/__init__.py
oda_data/api/__init__.py
oda_data/api/constants.py
oda_data/api/oecd.py
oda_data/api/representations.py
oda_data/api/sources.py
oda_data/clean_data/__init__.py
oda_data/clean_data/channels.py
oda_data/clean_data/common.py
oda_data/clean_data/crs_channel_mapping.csv
oda_data/clean_data/dtypes.py
oda_data/clean_data/schema.py
oda_data/clean_data/validation.py
oda_data/config.py
oda_data/indicators/__init__.py
oda_data/indicators/common.py
oda_data/indicators/crs/__init__.py
oda_data/indicators/crs/common.py
oda_data/indicators/crs/crs_functions.py
oda_data/indicators/crs/crs_indicators.json
oda_data/indicators/crs/oecd.py
oda_data/indicators/crs/one.py
oda_data/indicators/dac1/__init__.py
oda_data/indicators/dac1/common.py
oda_data/indicators/dac1/dac1_functions.py
oda_data/indicators/dac1/dac1_indicators.json
oda_data/indicators/dac1/oecd.py
oda_data/indicators/dac1/one.py
oda_data/indicators/dac2a/__init__.py
oda_data/indicators/dac2a/common.py
oda_data/indicators/dac2a/dac2a_functions.py
oda_data/indicators/dac2a/dac2a_indicators.json
oda_data/indicators/dac2a/oecd.py
oda_data/indicators/dac2a/one.py
oda_data/indicators/indicator.py
oda_data/indicators/research/__init__.py
oda_data/indicators/research/eu.py
oda_data/indicators/research/policy_markers.py
oda_data/indicators/research/sector_imputations.py
oda_data/logger.py
oda_data/oda_data_indicators.csv
oda_data/settings/crs_flow_types.json
oda_data/settings/crs_modalities.json
oda_data/settings/crs_policy_markers.json
oda_data/settings/crs_purpose.json
oda_data/settings/crs_type_of_finance.json
oda_data/settings/dac1_aid_flow_types.json
oda_data/settings/dac2a_aid_type.json
oda_data/settings/flow_types.json
oda_data/settings/indicators.json
oda_data/settings/key_columns.json
oda_data/settings/provider_groupings.json
oda_data/settings/recipient_groupings.json
oda_data/settings/v1_indicators_mapping.json
oda_data/tools/__init__.py
oda_data/tools/cache.py
oda_data/tools/compatibility.py
oda_data-2.4.1.dist-info/WHEEL
oda_data-2.4.1.dist-info/METADATA
oda_data-2.4.1.dist-info/RECORD
