Metadata-Version: 2.3
Name: oda-data
Version: 2.4.1
Summary: A python package to work with Official Development Assistance data from the OECD DAC.
Author: Jorge Rivera, Miguel Haro Ruiz
Author-email: Jorge Rivera <jorge.rivera@one.org>, Miguel Haro Ruiz <miguel.haroruiz@one.org>
License: MIT
Classifier: Development Status :: 5 - Production/Stable
Classifier: Intended Audience :: Developers
Classifier: Intended Audience :: Science/Research
Classifier: License :: OSI Approved :: MIT License
Classifier: Programming Language :: Python :: 3
Classifier: Programming Language :: Python :: 3.11
Classifier: Programming Language :: Python :: 3.12
Classifier: Programming Language :: Python :: 3.13
Classifier: Programming Language :: Python :: 3 :: Only
Classifier: Topic :: Scientific/Engineering
Classifier: Topic :: Software Development :: Libraries :: Python Modules
Requires-Dist: cachetools>=6.2.0
Requires-Dist: filelock>=3.20.0
Requires-Dist: oda-reader>=1.4.1
Requires-Dist: pandas[excel,parquet,performance]>=2.2.0
Requires-Dist: pydeflate>=2.3.3
Requires-Dist: reader>=3.18
Requires-Dist: thefuzz>=0.22.1
Requires-Python: >=3.11
Project-URL: Documentation, https://github.com/ONEcampaign/oda_data_package
Project-URL: Homepage, https://github.com/ONEcampaign/oda_data_package
Project-URL: Repository, https://github.com/ONEcampaign/oda_data_package
